nq/__init__.py
nq/hwp.py
nq/kk.py
nq/pnu.py
nq/rates.py
nq/sb.py
nq/sql.py
nq/test.py
nq/vid.py
nq/data/__init__.py
nq/data/bjd_20220401.pkl
nq/data/bjd_20220701.pkl
nq/data/bjd_20220901.pkl
nq/data/bjd_20230109.pkl
nq/data/bjd_20230611.pkl
nq/data/bjd_20230701.pkl
nq/data/bjd_20230703.pkl
nqnq-0.1.19.dist-info/LICENSE
nqnq-0.1.19.dist-info/METADATA
nqnq-0.1.19.dist-info/WHEEL
nqnq-0.1.19.dist-info/top_level.txt
nqnq-0.1.19.dist-info/RECORD
