Metadata-Version: 2.1
Name: nqnq
Version: 0.1.19
Author: nanangqq
Author-email: gingggg@gmail.com
Classifier: Programming Language :: Python :: 3
Classifier: License :: OSI Approved :: MIT License
Classifier: Operating System :: OS Independent
Requires-Python: >=3.9
License-File: LICENSE
Requires-Dist: requests
Requires-Dist: six
Requires-Dist: pyhwp
Requires-Dist: pandas
Requires-Dist: python-dotenv
